{"cameraMode":{"drawMode":0,"name":"Shaded","section":"Shading Mode"},"sceneLighting":true,"audioPlay":false,"sceneViewState":{"showFog":true,"showMaterialUpdate":false,"showSkybox":true,"showFlares":true,"showImageEffects":true,"showParticleSystems":true},"in2DMode":false,"pivot":{"x":559.9600219726563,"y":113.76249694824219,"z":-1.2600040435791016},"rotation":{"x":0.08741137385368347,"y":0.9124041795730591,"z":-0.2921683192253113,"w":0.27297550439834597},"size":1968.018798828125,"orthographic":false}